HISTORY.rst
LICENSE
MANIFEST.in
README.rst
setup.py
sprunge.py
sprunge.py.egg-info/PKG-INFO
sprunge.py.egg-info/SOURCES.txt
sprunge.py.egg-info/dependency_links.txt
sprunge.py.egg-info/requires.txt
sprunge.py.egg-info/top_level.txt